README.md
setup.py
stealchecker/__init__.py
stealchecker/stealchecker.py
stealchecker.egg-info/PKG-INFO
stealchecker.egg-info/SOURCES.txt
stealchecker.egg-info/dependency_links.txt
stealchecker.egg-info/entry_points.txt
stealchecker.egg-info/requires.txt
stealchecker.egg-info/top_level.txt