Metadata-Version: 2.1
Name: stealchecker
Version: 1.2.1
Summary: stealchecker: Checking CPU steal of VM from virtual host
Home-page: https://github.com/akam1o/stealchecker
Author: akam1o
Author-email: 5158577+akam1o@users.noreply.github.com
Maintainer: akam1o
Maintainer-email: 5158577+akam1o@users.noreply.github.com
License: MIT
Download-URL: https://github.com/akam1o/stealchecker
Keywords: libvirt kvm cpu steal
Platform: UNKNOWN
Classifier: License :: OSI Approved :: MIT License
Classifier: Programming Language :: Python :: 2 :: Only
